cli/__init__.py
cli/cli.py
yopass-cli/__init__.py
yopass_cli-0.0.2.dist-info/LICENSE
yopass_cli-0.0.2.dist-info/METADATA
yopass_cli-0.0.2.dist-info/WHEEL
yopass_cli-0.0.2.dist-info/entry_points.txt
yopass_cli-0.0.2.dist-info/top_level.txt
yopass_cli-0.0.2.dist-info/RECORD
